[
    {
        "categoria": "juegos",
        "pregunta": "¿Cuáles son los juegos favoritos de Kevin?",
        "respuesta": "Valorant, League of Legends",
        "incorrecta1": "5 Noches con Alfredo",
        "incorrecta2": "Overwatch",
        "incorrecta3": "Pokémon Go"
    },
    {
        "categoria": "personajes de Valorant",
        "pregunta": "¿Cuál es el personaje favorito de Kevin en Valorant?",
        "respuesta": "Jett",
        "incorrecta1": "Omen",
        "incorrecta2": "Raze",
        "incorrecta3": "Killjoy"
    },
    {
        "categoria": "Personajes de League of Legends",
        "pregunta": "¿Cuál es el personaje favorito de Kevin en League of Legends?",
        "respuesta": "Kai'Sa",
        "incorrecta1": "Lee Sin",
        "incorrecta2": "Warwick",
        "incorrecta3": "Irelia"
    },
    {
        "categoria": "Comida",
        "pregunta": "cual es la comida favorita de Kevin?",
        "respuesta": "Pupusas lasagna pizza",
        "incorrecta1": "Arepas",
        "incorrecta2": "tortilla de patatas",
        "incorrecta3": "Salchichas"
    },
    {
        "categoria": "Comida",
        "pregunta": "Cual es la comida que no le gusta a Kevin?",
        "respuesta": "Salchichas",
        "incorrecta1": "Arepas",
        "incorrecta2": "chiles rellenos",
        "incorrecta3": "Sopas "
    },
    {
        "categoria": "Comida",
        "pregunta": "Cual es la comida que no le gusta a Kevin?",
        "respuesta": "Salchichas",
        "incorrecta1": "Arepas",
        "incorrecta2": "chiles rellenos",
        "incorrecta3": "Sopas "
    }

]
